storage/__init__.py
storage/storage_main.py
storage/storagelib.py
pyros_storage-1.1.0.dist-info/LICENSE
pyros_storage-1.1.0.dist-info/METADATA
pyros_storage-1.1.0.dist-info/WHEEL
pyros_storage-1.1.0.dist-info/top_level.txt
pyros_storage-1.1.0.dist-info/RECORD
