Metadata-Version: 2.1
Name: pyros-storage
Version: 1.1.0
Summary: PyROS Storage
Home-page: https://github.com/Abstract-Horizon/pyros-storage
Author: Daniel Sendula
License: UNKNOWN
Platform: UNKNOWN
Classifier: Programming Language :: Python :: 3
Classifier: License :: OSI Approved :: Apache Software License
Classifier: Operating System :: OS Independent
Requires-Python: >=3.6
License-File: LICENSE
Requires-Dist: pyros-client
